README.md
setup.py
labelizer/AuxiliaryFunction.py
labelizer/ChargeEnvTestFile.py
labelizer/ChargeEnvironment.py
labelizer/ConservationScore.py
labelizer/Constants.py
labelizer/CysteineResemblance.py
labelizer/FRETScore.py
labelizer/LabelLibFunctions.py
labelizer/LabelLibProteinTest.py
labelizer/LabelLibTest.py
labelizer/LabelingParameter.py
labelizer/Labelizer.py
labelizer/LabelizerTest.py
labelizer/Labelizer_script.py
labelizer/MeasurementScore.py
labelizer/SecondaryStructure.py
labelizer/SolventExposure.py
labelizer/SurfaceTest.py
labelizer/TryptophanProximity.py
labelizer/__init__.py
labelizer/pdbhelper.py
labelizer/readPDB.py
labelizer.egg-info/PKG-INFO
labelizer.egg-info/SOURCES.txt
labelizer.egg-info/dependency_links.txt
labelizer.egg-info/requires.txt
labelizer.egg-info/top_level.txt