Metadata-Version: 2.1
Name: labelizer
Version: 0.0.0b1
Summary: Protein analysis toolbox for fluorescent labelling and FRET assays
Home-page: https://github.com/ChristianGebhardt/labelizer
Author: Christian Gebhardt
Author-email: christian.gebhardt@bio.lmu.de
License: MIT
Download-URL: https://pypi.org/project/labelizer/
Keywords: fluorescent label analysis,FRET assay
Platform: UNKNOWN
